Metadata-Version: 1.0
Name: pd-gb
Version: 1.0
Summary: Gaussian and Binomial distributions
Home-page: UNKNOWN
Author: Charleen Lozi
Author-email: clozymwangs@gmail.com
License: UNKNOWN
Platform: UNKNOWN
